discord/ext/paginator/__init__.py
discord_ext_paginator-0.4.6.dist-info/LICENSE
discord_ext_paginator-0.4.6.dist-info/METADATA
discord_ext_paginator-0.4.6.dist-info/WHEEL
discord_ext_paginator-0.4.6.dist-info/top_level.txt
discord_ext_paginator-0.4.6.dist-info/RECORD
