Metadata-Version: 2.1
Name: discord-ext-paginator
Version: 0.4.6
Summary: An package for discord pagination.
Home-page: UNKNOWN
Author: Alex Hutz
Author-email: frostiiflames@gmail.com
License: MIT
Keywords: discord.py,paginator
Platform: UNKNOWN
Requires-Python: >=3.7.1
Requires-Dist: discord.py (>=1.5.1)
